tencentcloud/__init__.py
tencentcloud/rce/__init__.py
tencentcloud/rce/v20201103/__init__.py
tencentcloud/rce/v20201103/errorcodes.py
tencentcloud/rce/v20201103/models.py
tencentcloud/rce/v20201103/rce_client.py
tencentcloud/rce/v20201103/rce_client_async.py
tencentcloud/rce/v20250425/__init__.py
tencentcloud/rce/v20250425/errorcodes.py
tencentcloud/rce/v20250425/models.py
tencentcloud/rce/v20250425/rce_client.py
tencentcloud/rce/v20250425/rce_client_async.py
tencentcloud_sdk_python_rce-3.1.35.dist-info/METADATA
tencentcloud_sdk_python_rce-3.1.35.dist-info/WHEEL
tencentcloud_sdk_python_rce-3.1.35.dist-info/top_level.txt
tencentcloud_sdk_python_rce-3.1.35.dist-info/RECORD
